devtools_byte_counter/__init__.py
devtools_byte_counter-1.0.1.dist-info/METADATA
devtools_byte_counter-1.0.1.dist-info/WHEEL
devtools_byte_counter-1.0.1.dist-info/top_level.txt
devtools_byte_counter-1.0.1.dist-info/RECORD
