Metadata-Version: 2.1
Name: devtools-byte-counter
Version: 1.0.1
Summary: Byte and character counter
Home-page: https://devtools.at/tools/byte-counter
Author: DevTools.at
Author-email: hello@devtools.at
Project-URL: Homepage, https://devtools.at/tools/byte-counter
Project-URL: Repository, https://github.com/devtools-at/byte-counter
Classifier: Development Status :: 4 - Beta
Classifier: Intended Audience :: Developers
Classifier: License :: OSI Approved :: MIT License
Classifier: Programming Language :: Python :: 3
Requires-Python: >=3.8
